dpgdesigner/__init__.py
dpgdesigner/style_theme.py
dpgdesigner/utils.py
dpgdesigner/fonts/FiraCode-SemiBold.ttf
dpgdesigner-0.0.4.dist-info/LICENSE
dpgdesigner-0.0.4.dist-info/METADATA
dpgdesigner-0.0.4.dist-info/WHEEL
dpgdesigner-0.0.4.dist-info/top_level.txt
dpgdesigner-0.0.4.dist-info/RECORD
