Metadata-Version: 2.1
Name: dpgdesigner
Version: 0.0.4
Summary: A designer for dear py gui. Allows you to create dpg apps visually with a UI for making the UI
Author: Matthew Sanchez
Author-email: xxspicymelonxx@gmail.com
Classifier: Programming Language :: Python :: 3
Classifier: License :: OSI Approved :: MIT License
Classifier: Operating System :: OS Independent
Requires-Python: >=3.10
License-File: LICENSE
Requires-Dist: dearpygui
Requires-Dist: screeninfo
